library_sonya/__init__.py
sonya_library-1.0.dist-info/METADATA
sonya_library-1.0.dist-info/WHEEL
sonya_library-1.0.dist-info/top_level.txt
sonya_library-1.0.dist-info/RECORD
