Metadata-Version: 2.1
Name: sonya-library
Version: 1.0
Summary: библиотека по обработке текстов
Home-page: https://github.com/SofiaGalinovskaya/sonya_progect
Author: Sofia_66
Author-email: Sonushock@gmail.com
License: UNKNOWN
Platform: UNKNOWN
Classifier: Programming Language :: Python :: 3
Classifier: License :: OSI Approved :: MIT License
Classifier: Operating System :: OS Independent
Requires-Python: >=3.6
